readmint/__about__.py
readmint/__init__.py
readmint/__main__.py
readmint/cli/__init__.py
readmint-0.0.1.dist-info/METADATA
readmint-0.0.1.dist-info/WHEEL
readmint-0.0.1.dist-info/entry_points.txt
readmint-0.0.1.dist-info/licenses/LICENSE.md
readmint-0.0.1.dist-info/licenses/LICENSE.txt
readmint-0.0.1.dist-info/RECORD
