Metadata-Version: 2.1
Name: readmint
Version: 0.0.1
Project-URL: Documentation, https://github.com/unknown/readmint#readme
Project-URL: Issues, https://github.com/unknown/readmint/issues
Project-URL: Source, https://github.com/unknown/readmint
Author-email: Alvaro Leiva Geisse <aleivag@gmail.com>
License: MIT License
License-File: LICENSE.md
License-File: LICENSE.txt
Classifier: Development Status :: 4 - Beta
Classifier: Programming Language :: Python
Classifier: Programming Language :: Python :: 3.7
Classifier: Programming Language :: Python :: 3.8
Classifier: Programming Language :: Python :: 3.9
Classifier: Programming Language :: Python :: 3.10
Classifier: Programming Language :: Python :: 3.11
Classifier: Programming Language :: Python :: Implementation :: CPython
Classifier: Programming Language :: Python :: Implementation :: PyPy
Requires-Python: >=3.7
Requires-Dist: click
Requires-Dist: ipython
Requires-Dist: marko
